odoo/addons/l10n_ro_stock_picking_comment_template/README.rst
odoo/addons/l10n_ro_stock_picking_comment_template/__init__.py
odoo/addons/l10n_ro_stock_picking_comment_template/__manifest__.py
odoo/addons/l10n_ro_stock_picking_comment_template/data/l10n_ro_stock_picking_comment_template.xml
odoo/addons/l10n_ro_stock_picking_comment_template/i18n/l10n_ro_stock_picking_comment_template.pot
odoo/addons/l10n_ro_stock_picking_comment_template/i18n/ro.po
odoo/addons/l10n_ro_stock_picking_comment_template/migrations/14.0.1.1.1/pre-migration.py
odoo/addons/l10n_ro_stock_picking_comment_template/models/__init__.py
odoo/addons/l10n_ro_stock_picking_comment_template/models/comment_template.py
odoo/addons/l10n_ro_stock_picking_comment_template/models/res_partner.py
odoo/addons/l10n_ro_stock_picking_comment_template/models/stock_picking.py
odoo/addons/l10n_ro_stock_picking_comment_template/readme/CONTRIBUTORS.rst
odoo/addons/l10n_ro_stock_picking_comment_template/readme/DESCRIPTION.rst
odoo/addons/l10n_ro_stock_picking_comment_template/readme/USAGE.rst
odoo/addons/l10n_ro_stock_picking_comment_template/security/ir.model.access.csv
odoo/addons/l10n_ro_stock_picking_comment_template/static/description/icon.png
odoo/addons/l10n_ro_stock_picking_comment_template/static/description/icon.svg
odoo/addons/l10n_ro_stock_picking_comment_template/static/description/index.html
odoo/addons/l10n_ro_stock_picking_comment_template/views/base_comment_template_view.xml
odoo/addons/l10n_ro_stock_picking_comment_template/views/report_delivery_document.xml
odoo/addons/l10n_ro_stock_picking_comment_template/views/report_picking.xml
odoo/addons/l10n_ro_stock_picking_comment_template/views/stock_picking_view.xml
odoo14_addon_l10n_ro_stock_picking_comment_template-14.0.2.6.0.dist-info/METADATA
odoo14_addon_l10n_ro_stock_picking_comment_template-14.0.2.6.0.dist-info/WHEEL
odoo14_addon_l10n_ro_stock_picking_comment_template-14.0.2.6.0.dist-info/top_level.txt
odoo14_addon_l10n_ro_stock_picking_comment_template-14.0.2.6.0.dist-info/RECORD
