Metadata-Version: 2.1
Name: odoo14-addon-l10n-ro-stock-picking-comment-template
Version: 14.0.2.6.0
Summary: This model is going to add a a header and a footer at picking report depeding on the operation type.
Home-page: https://github.com/OCA/l10n-romania
Author: NextERP Romania,Odoo Community Association (OCA)
Author-email: support@odoo-community.org
License: AGPL-3
Platform: UNKNOWN
Classifier: Programming Language :: Python
Classifier: Framework :: Odoo
Classifier: Framework :: Odoo :: 14.0
Classifier: License :: OSI Approved :: GNU Affero General Public License v3
Classifier: Development Status :: 4 - Beta
Requires-Python: >=3.6
Requires-Dist: odoo14-addon-base-comment-template
Requires-Dist: odoo14-addon-l10n-ro-stock-account
Requires-Dist: odoo <14.1dev,>=14.0a
